misp_modules/__init__.py
misp_modules/__main__.py
misp_modules/lib/ODTReader/LICENSE
misp_modules/lib/ODTReader/__init__.py
misp_modules/lib/ODTReader/odtreader.py
misp_modules/lib/ODTReader/win32_unicode_argv.py
misp_modules/lib/__init__.py
misp_modules/lib/_vmray/__init__.py
misp_modules/lib/_vmray/parser.py
misp_modules/lib/_vmray/rest_api.py
misp_modules/lib/cof2misp/LICENSE-2.0.txt
misp_modules/lib/cof2misp/__init__.py
misp_modules/lib/cof2misp/cof.py
misp_modules/lib/dnstrails/LICENSE
misp_modules/lib/dnstrails/__init__.py
misp_modules/lib/dnstrails/api.py
misp_modules/lib/dnstrails/exception.py
misp_modules/lib/joe_mapping.py
misp_modules/lib/joe_parser.py
misp_modules/lib/lastline_api.py
misp_modules/lib/onyphe/LICENSE
misp_modules/lib/onyphe/__init__.py
misp_modules/lib/onyphe/client.py
misp_modules/lib/onyphe/exception.py
misp_modules/lib/qintel_helper.py
misp_modules/lib/synonymsToTagNames.json
misp_modules/lib/vt_graph_parser/__init__.py
misp_modules/lib/vt_graph_parser/errors.py
misp_modules/lib/vt_graph_parser/helpers/__init__.py
misp_modules/lib/vt_graph_parser/helpers/parsers.py
misp_modules/lib/vt_graph_parser/helpers/rules.py
misp_modules/lib/vt_graph_parser/helpers/wrappers.py
misp_modules/lib/vt_graph_parser/importers/__init__.py
misp_modules/lib/vt_graph_parser/importers/base.py
misp_modules/lib/vt_graph_parser/importers/pymisp_response.py
misp_modules/modules/__init__.py
misp_modules/modules/action_mod/__init__.py
misp_modules/modules/action_mod/_utils/__init__.py
misp_modules/modules/action_mod/_utils/utils.py
misp_modules/modules/action_mod/mattermost.py
misp_modules/modules/action_mod/slack.py
misp_modules/modules/action_mod/testaction.py
misp_modules/modules/expansion/__init__.py
misp_modules/modules/expansion/_dnsdb_query/COPYRIGHT
misp_modules/modules/expansion/_dnsdb_query/LICENSE
misp_modules/modules/expansion/_dnsdb_query/README.md
misp_modules/modules/expansion/_dnsdb_query/__init__.py
misp_modules-3.0.1.dist-info/LICENSE
misp_modules-3.0.1.dist-info/METADATA
misp_modules-3.0.1.dist-info/WHEEL
misp_modules-3.0.1.dist-info/entry_points.txt
misp_modules-3.0.1.dist-info/RECORD
