Metadata-Version: 2.3
Name: misp-modules
Version: 3.0.1
Summary: MISP modules are autonomous modules that can be used for expansion and other services in MISP
License: AGPL-3.0-only
Author: Alexandre Dulaunoy
Author-email: alexandre.dulaunoy@circl.lu
Requires-Python: >=3.9,<3.13
Classifier: License :: OSI Approved :: GNU Affero General Public License v3
Classifier: Development Status :: 5 - Production/Stable
Classifier: Environment :: Console
Classifier: Intended Audience :: Science/Research
Classifier: Programming Language :: Python :: 3
Classifier: Topic :: Security
Provides-Extra: all
Requires-Dist: apiosintds ; extra == "all"
Requires-Dist: assemblyline_client ; extra == "all"
Requires-Dist: backscatter ; extra == "all"
Requires-Dist: beautifulsoup4
Requires-Dist: blockchain ; extra == "all"
Requires-Dist: censys (==2.0.9) ; extra == "all"
Requires-Dist: clamd ; extra == "all"
Requires-Dist: crowdstrike-falconpy ; extra == "all"
Requires-Dist: dnsdb2 ; extra == "all"
Requires-Dist: domaintools_api ; extra == "all"
Requires-Dist: geoip2 ; extra == "all"
Requires-Dist: greynoise ; extra == "all"
Requires-Dist: jbxapi ; extra == "all"
Requires-Dist: jinja2
Requires-Dist: maclookup ; extra == "all"
Requires-Dist: markdownify
Requires-Dist: matplotlib ; extra == "all"
Requires-Dist: mattermostdriver ; extra == "all"
Requires-Dist: misp-lib-stix2 (>=3.0.1.2) ; extra == "all"
Requires-Dist: misp-stix (>=2025.1.10) ; extra == "all"
Requires-Dist: mwdblib ; extra == "all"
Requires-Dist: ndjson ; extra == "all"
Requires-Dist: np ; extra == "all"
Requires-Dist: numpy (>=1.26.4,<2.0.0) ; extra == "all"
Requires-Dist: oauth2 ; extra == "all"
Requires-Dist: opencv-python ; extra == "all"
Requires-Dist: openpyxl ; extra == "all"
Requires-Dist: orjson
Requires-Dist: pandas (>=2.0.0) ; extra == "all"
Requires-Dist: pandas_ods_reader (>=1.0.0) ; extra == "all"
Requires-Dist: pandoc ; extra == "all"
Requires-Dist: passivetotal ; extra == "all"
Requires-Dist: pdftotext ; extra == "all"
Requires-Dist: psutil
Requires-Dist: publicsuffixlist
Requires-Dist: pycountry ; extra == "all"
Requires-Dist: pyeti-python3 ; extra == "all"
Requires-Dist: pyeupi ; extra == "all"
Requires-Dist: pygeoip ; extra == "all"
Requires-Dist: pyintel471 ; extra == "all"
Requires-Dist: pyipasnhistory ; extra == "all"
Requires-Dist: pymisp
Requires-Dist: pymisp[email,fileobjects,openioc,pdfexport] ; extra == "all"
Requires-Dist: pypdns ; extra == "all"
Requires-Dist: pypssl ; extra == "all"
Requires-Dist: pysafebrowsing ; extra == "all"
Requires-Dist: pytesseract ; extra == "all"
Requires-Dist: python-docx ; extra == "all"
Requires-Dist: python-pptx ; extra == "all"
Requires-Dist: pyzbar ; extra == "all"
Requires-Dist: requests[security] ; extra == "all"
Requires-Dist: setuptools
Requires-Dist: setuptools ; extra == "all"
Requires-Dist: shodan ; extra == "all"
Requires-Dist: sigmatools ; extra == "all"
Requires-Dist: sigmf ; extra == "all"
Requires-Dist: slack-sdk ; extra == "all"
Requires-Dist: socialscan (<2.0.0) ; extra == "all"
Requires-Dist: sparqlwrapper ; extra == "all"
Requires-Dist: tau-clients ; extra == "all"
Requires-Dist: taxii2-client ; extra == "all"
Requires-Dist: tornado
Requires-Dist: trustar ; extra == "all"
Requires-Dist: urlarchiver ; extra == "all"
Requires-Dist: vt-graph-api ; extra == "all"
Requires-Dist: vt-py ; extra == "all"
Requires-Dist: vulners ; extra == "all"
Requires-Dist: vysion ; extra == "all"
Requires-Dist: wand ; extra == "all"
Requires-Dist: xlrd ; extra == "all"
Requires-Dist: yara-python (==4.5.0) ; extra == "all"
Project-URL: Documentation, https://misp.github.io/misp-modules
Project-URL: Homepage, https://github.com/MISP/misp-modules
Project-URL: Issues, https://github.com/MISP/misp-modules/issues
Project-URL: Repository, https://github.com/MISP/misp-modules
